Changelog.rst
Developer_Manual.rst
LICENSE.txt
MANIFEST.in
README.rst
pyproject.toml
setup.cfg
setup.py
SajodeSx/Builtins.py
SajodeSx/BytecodeCaching.py
SajodeSx/Bytecodes.py
SajodeSx/CacheCleanup.py
SajodeSx/Constants.py
SajodeSx/Errors.py
SajodeSx/HardImportRegistry.py
SajodeSx/MainControl.py
SajodeSx/ModuleRegistry.py
SajodeSx/OptionParsing.py
SajodeSx/Options.py
SajodeSx/OutputDirectories.py
SajodeSx/PostProcessing.py
SajodeSx/Progress.py
SajodeSx/PythonFlavors.py
SajodeSx/PythonOperators.py
SajodeSx/PythonVersions.py
SajodeSx/Serialization.py
SajodeSx/SourceCodeReferences.py
SajodeSx/Tracing.py
SajodeSx/TreeXML.py
SajodeSx/Variables.py
SajodeSx/Version.py
SajodeSx/__init__.py
SajodeSx/__main__.py
SajodeSx/__past__.py
SajodeSx/build/Backend.scons
SajodeSx/build/CCompilerVersion.scons
SajodeSx/build/DataComposerInterface.py
SajodeSx/build/Offsets.scons
SajodeSx/build/Onefile.scons
SajodeSx/build/SconsCaching.py
SajodeSx/build/SconsCompilerSettings.py
SajodeSx/build/SconsHacks.py
SajodeSx/build/SconsInterface.py
SajodeSx/build/SconsProgress.py
SajodeSx/build/SconsSpawn.py
SajodeSx/build/SconsUtils.py
SajodeSx/build/__init__.py
SajodeSx/build/include/SajodeSx/allocator.h
SajodeSx/build/include/SajodeSx/builtins.h
SajodeSx/build/include/SajodeSx/calling.h
SajodeSx/build/include/SajodeSx/checkers.h
SajodeSx/build/include/SajodeSx/checksum_tools.h
SajodeSx/build/include/SajodeSx/compiled_asyncgen.h
SajodeSx/build/include/SajodeSx/compiled_cell.h
SajodeSx/build/include/SajodeSx/compiled_coroutine.h
SajodeSx/build/include/SajodeSx/compiled_frame.h
SajodeSx/build/include/SajodeSx/compiled_function.h
SajodeSx/build/include/SajodeSx/compiled_generator.h
SajodeSx/build/include/SajodeSx/compiled_method.h
SajodeSx/build/include/SajodeSx/constants.h
SajodeSx/build/include/SajodeSx/constants_blob.h
SajodeSx/build/include/SajodeSx/debug_settings.h
SajodeSx/build/include/SajodeSx/environment_variables.h
SajodeSx/build/include/SajodeSx/environment_variables_system.h
TeamYousef.egg-info/PKG-INFO
TeamYousef.egg-info/SOURCES.txt
TeamYousef.egg-info/dependency_links.txt
TeamYousef.egg-info/top_level.txt
